iso3166/__init__.py
iso3166/py.typed
iso3166-2.1.0.dist-info/LICENSE.txt
iso3166-2.1.0.dist-info/METADATA
iso3166-2.1.0.dist-info/WHEEL
iso3166-2.1.0.dist-info/top_level.txt
iso3166-2.1.0.dist-info/RECORD
