Metadata-Version: 2.1
Name: iso3166
Version: 2.1.0
Summary: Self-contained ISO 3166-1 country definitions.
Home-page: http://github.com/deactivated/python-iso3166
Author: Mike Spindel
Author-email: mike@spindel.is
License: MIT
Keywords: iso 3166-1 country codes
Platform: UNKNOWN
Classifier: Development Status :: 5 - Production/Stable
Classifier: License :: OSI Approved :: MIT License
Classifier: Intended Audience :: Developers
Classifier: Natural Language :: English
Classifier: Programming Language :: Python
Classifier: Programming Language :: Python :: 3
Classifier: Programming Language :: Python :: 3 :: Only
Classifier: Programming Language :: Python :: 3.6
Classifier: Programming Language :: Python :: 3.7
Classifier: Programming Language :: Python :: 3.8
Classifier: Programming Language :: Python :: 3.9
Classifier: Programming Language :: Python :: 3.10
Requires-Python: >= 3.6
License-File: LICENSE.txt
